[
    {"date": "01/01/2018", "company": "Shell",      "spend": 37, "litres": 30, "miles": 414},
    {"date": "08/01/2018", "company": "BP",         "spend": 39, "litres": 31, "miles": 400},
    {"date": "14/01/2018", "company": "Sainsburys", "spend": 38, "litres": 31, "miles": 417},
    {"date": "21/01/2018", "company": "Sainsburys", "spend": 39, "litres": 32, "miles": 415},
    {"date": "28/01/2018", "company": "Sainsburys", "spend": 39, "litres": 32, "miles": 407},
    {"date": "16/04/2018", "company": "BP",         "spend": 38, "litres": 31, "miles": 409},
    {"date": "25/04/2018", "company": "BP",         "spend": 20, "litres": 16, "miles": 240},
    {"date": "30/04/2018", "company": "BP",         "spend": 39, "litres": 31, "miles": 381},
    {"date": "08/05/2018", "company": "BP",         "spend": 40, "litres": 31, "miles": 449},
    {"date": "16/05/2018", "company": "BP",         "spend": 39, "litres": 30, "miles": 405},
    {"date": "23/05/2018", "company": "Sainsburys", "spend": 40, "litres": 31, "miles": 418},
    {"date": "01/06/2018", "company": "BP",         "spend": 40, "litres": 30, "miles": 418},
    {"date": "08/06/2018", "company": "BP",         "spend": 41, "litres": 31, "miles": 445},
    {"date": "15/06/2018", "company": "BP",         "spend": 40, "litres": 31, "miles": 405},
    {"date": "25/06/2018", "company": "BP",         "spend": 42, "litres": 32, "miles": 454},
    {"date": "01/07/2018", "company": "BP",         "spend": 42, "litres": 33, "miles": 450},
    {"date": "08/07/2018", "company": "Applegreen", "spend": 40, "litres": 32, "miles": 433},
    {"date": "16/07/2018", "company": "BP",         "spend": 40, "litres": 31, "miles": 464},
    {"date": "24/07/2018", "company": "BP",         "spend": 40, "litres": 31, "miles": 478},
    {"date": "01/08/2018", "company": "Shell",      "spend": 38, "litres": 29, "miles": 378},
    {"date": "01/09/2018", "company": "Applegreen", "spend": 40, "litres": 31, "miles": 409},
    {"date": "06/10/2018", "company": "Shell",      "spend": 40, "litres": 27, "miles": 377},
    {"date": "20/10/2018", "company": "Shell",      "spend": 35, "litres": 23, "miles": 320},
    {"date": "24/10/2018", "company": "BP",         "spend": 40, "litres": 30, "miles": 407},
    {"date": "01/11/2018", "company": "BP",         "spend": 39, "litres": 29, "miles": 372},
    {"date": "07/11/2018", "company": "Sainsburys", "spend": 39, "litres": 30, "miles": 386},
    {"date": "14/11/2018", "company": "BP",         "spend": 40, "litres": 30, "miles": 390},
    {"date": "21/11/2018", "company": "BP",         "spend": 40, "litres": 30, "miles": 440},
    {"date": "28/11/2018", "company": "BP",         "spend": 41, "litres": 31, "miles": 325},
    {"date": "04/12/2018", "company": "Sainsburys", "spend": 40, "litres": 32, "miles": 398},
    {"date": "09/12/2018", "company": "Shell",      "spend": 40, "litres": 28, "miles": 350},
    {"date": "13/12/2018", "company": "Esso",       "spend": 22, "litres": 17, "miles": 237},
    {"date": "18/12/2018", "company": "BP",         "spend": 40, "litres": 31, "miles": 394},
    {"date": "24/12/2018", "company": "BP",         "spend": 39, "litres": 31, "miles": 399}
]  
    
    
    
    
    
    
    
    
    
    
    
    
    
    
    
    
    
    
    
    
    
    
]    
    